modyaml/__init__.py
modyaml/readme.md
modyaml-0.0.post26.dist-info/METADATA
modyaml-0.0.post26.dist-info/WHEEL
modyaml-0.0.post26.dist-info/top_level.txt
modyaml-0.0.post26.dist-info/RECORD
