Metadata-Version: 2.4
Name: modyaml
Version: 0.0.post26
Summary: Modular Yaml for configuration management
Author-email: AlexMKX <pypi-alex@xxl.cx>
License: BSD 3-Clause License
Classifier: License :: OSI Approved :: BSD License
Classifier: Programming Language :: Python :: 3
Requires-Dist: pyyaml>=6.0.1
Requires-Dist: jinja2>=3.1.2
Requires-Dist: pyyaml-include>=1.3.1
Requires-Dist: fsspec>=2023.12.2
